odoo10_addon_res_country_state_translations_us-10.0.1.0.0.99.dev4-py3.8-nspkg.pth
odoo/addons/res_country_state_translations_us/README.rst
odoo/addons/res_country_state_translations_us/__init__.py
odoo/addons/res_country_state_translations_us/__manifest__.py
odoo/addons/res_country_state_translations_us/i18n/fr.po
odoo/addons/res_country_state_translations_us/i18n/res_country_state_translations_us.pot
odoo/addons/res_country_state_translations_us/i18n_extra/fr.po
odoo/addons/res_country_state_translations_us/readme/CONTRIBUTORS.rst
odoo/addons/res_country_state_translations_us/readme/DESCRIPTION.rst
odoo/addons/res_country_state_translations_us/static/description/icon.png
odoo/addons/res_country_state_translations_us/static/description/index.html
odoo10_addon_res_country_state_translations_us-10.0.1.0.0.99.dev4.dist-info/METADATA
odoo10_addon_res_country_state_translations_us-10.0.1.0.0.99.dev4.dist-info/WHEEL
odoo10_addon_res_country_state_translations_us-10.0.1.0.0.99.dev4.dist-info/namespace_packages.txt
odoo10_addon_res_country_state_translations_us-10.0.1.0.0.99.dev4.dist-info/top_level.txt
odoo10_addon_res_country_state_translations_us-10.0.1.0.0.99.dev4.dist-info/RECORD
